jp_medicine_master/__init__.py
jp_medicine_master/master.py
jp_medicine_master/usage.py
jp_medicine_master-2.0.2.dist-info/licenses/LICENSE
jp_medicine_master-2.0.2.dist-info/METADATA
jp_medicine_master-2.0.2.dist-info/WHEEL
jp_medicine_master-2.0.2.dist-info/top_level.txt
jp_medicine_master-2.0.2.dist-info/RECORD
