Metadata-Version: 2.4
Name: jp_medicine_master
Version: 2.0.2
Summary: 日本で使用される医薬品マスタを簡単に取得・利用するためのライブラリ
Author-email: SHIRO <shiro46mt@gmail.com>
License-Expression: MIT
Project-URL: Repository, https://github.com/shiro46mt/jp-medicine-master.git
Classifier: Development Status :: 5 - Production/Stable
Classifier: Programming Language :: Python :: 3
Classifier: Topic :: Scientific/Engineering :: Bio-Informatics
Classifier: Topic :: Scientific/Engineering :: Medical Science Apps.
Classifier: Natural Language :: Japanese
Requires-Python: >=3.9
License-File: LICENSE
Requires-Dist: pandas
Requires-Dist: requests
Dynamic: license-file
